README.md
setup.py
pointgrid/__init__.py
pointgrid/pointgrid.py
pointgrid.egg-info/PKG-INFO
pointgrid.egg-info/SOURCES.txt
pointgrid.egg-info/dependency_links.txt
pointgrid.egg-info/requires.txt
pointgrid.egg-info/top_level.txt