Metadata-Version: 1.0
Name: pointgrid
Version: 0.0.5
Summary: Transform a 2D distribution into a hexagonal layout
Home-page: https://github.com/yaledhlab/pointgrid
Author: Douglas Duhaime
Author-email: douglas.duhaime@gmail.com
License: MIT
Keywords: data-visualization,scatterplots,pointcloud,overplotting
Platform: UNKNOWN
